{
  "$schema": "https://schemas.wp.org/trunk/block.json",
  "apiVersion": 2,
  "name": "mortgage/button",
  "ancestor": [
    "mortgage/form"
  ],
  "title": "Button",
  "icon": "button",
  "textdomain": "mortgage",
  "attributes": {
    "lock": {
      "type": "object",
      "default": {
        "move": true,
        "remove": true
      }
    },
    "text": {
      "type": "string",
      "default": "Calculate"
    },
    "alignment": {
      "type": "string",
      "default": "left"
    },
    "style": {
      "type": "object",
      "default": {
        "color": {
          "background": "#000000",
          "text": "#ffffff"
        }
      }
    }
  },
  "supports": {
    "html": false,
    "lock": false,
    "multiple": false,
    "reusable": false,
    "className": false,
    "color": {
      "background": true,
      "text": true,
      "gradients": true
    },
    "__experimentalBorder": true,
    "spacing": {
      "padding": true,
      "__experimentalDefaultControls": {
        "padding": true
      }
    }
  }
}